{".class": "MypyFile", "_fullname": "proyecto_es_primo_boosted", "is_partial_stub_package": false, "is_stub": false, "names": {".class": "SymbolTable", "__doc__": {".class": "SymbolTableNode", "kind": "Gdef", "node": {".class": "Var", "flags": ["is_ready"], "fullname": "proyecto_es_primo_boosted.__doc__", "name": "__doc__", "type": "builtins.str"}}, "__file__": {".class": "SymbolTableNode", "kind": "Gdef", "node": {".class": "Var", "flags": ["is_ready"], "fullname": "proyecto_es_primo_boosted.__file__", "name": "__file__", "type": "builtins.str"}}, "__name__": {".class": "SymbolTableNode", "kind": "Gdef", "node": {".class": "Var", "flags": ["is_ready"], "fullname": "proyecto_es_primo_boosted.__name__", "name": "__name__", "type": "builtins.str"}}, "__package__": {".class": "SymbolTableNode", "kind": "Gdef", "node": {".class": "Var", "flags": ["is_ready"], "fullname": "proyecto_es_primo_boosted.__package__", "name": "__package__", "type": "builtins.str"}}, "es_primo": {".class": "SymbolTableNode", "kind": "Gdef", "node": {".class": "FuncDef", "arg_kinds": [0], "arg_names": ["numero"], "flags": [], "fullname": "proyecto_es_primo_boosted.es_primo", "name": "es_primo", "type": {".class": "CallableType", "arg_kinds": [0], "arg_names": ["numero"], "arg_types": ["builtins.int"], "bound_args": [], "def_extras": {"first_arg": null}, "fallback": "builtins.function", "implicit": false, "is_ellipsis_args": false, "name": "es_primo", "ret_type": "builtins.bool", "type_guard": null, "variables": []}}}, "run": {".class": "SymbolTableNode", "kind": "Gdef", "node": {".class": "FuncDef", "arg_kinds": [], "arg_names": [], "flags": [], "fullname": "proyecto_es_primo_boosted.run", "name": "run", "type": null}}}, "path": "proyecto_es_primo_boosted.py"}